cosmic_unified_sim-0.2.0.dist-info/licenses/LICENSE
sim/__init__.py
sim/cli/__init__.py
sim/cli/main.py
sim/coherence/__init__.py
sim/coherence/models.py
sim/coherence/simulator.py
sim/constants/__init__.py
sim/constants/cosmological.py
sim/constants/fundamental.py
sim/core/__init__.py
sim/core/base.py
sim/core/checkpoint.py
sim/core/config.py
sim/core/exceptions.py
sim/core/gpu.py
sim/core/io.py
sim/core/logging.py
sim/core/progress.py
sim/cosmic/__init__.py
sim/cosmic/body.py
sim/cosmic/calculator.py
sim/cosmic/integrators.py
sim/cosmic/nbody.py
sim/cosmic/presets.py
sim/genesis/__init__.py
sim/genesis/leptogenesis.py
sim/genesis/quantum_creation.py
sim/genesis/resonance.py
sim/genesis/simulation.py
sim/holographic/__init__.py
sim/holographic/analysis.py
sim/holographic/report.py
sim/quantum/__init__.py
sim/quantum/emergence.py
sim/quantum/fabric.py
sim/quantum/observer.py
sim/quantum/operators.py
sim/visualization/__init__.py
sim/visualization/plots.py
cosmic_unified_sim-0.2.0.dist-info/METADATA
cosmic_unified_sim-0.2.0.dist-info/WHEEL
cosmic_unified_sim-0.2.0.dist-info/entry_points.txt
cosmic_unified_sim-0.2.0.dist-info/top_level.txt
cosmic_unified_sim-0.2.0.dist-info/RECORD
