Metadata-Version: 2.4
Name: cosmic-unified-sim
Version: 0.2.0
Summary: Unified cosmological simulation framework: quantum mechanics, N-body dynamics, coherence evolution, matter genesis, and holographic analysis
Author-email: Timur Isanov <tisanov@yahoo.com>
License: MIT
Project-URL: Homepage, https://github.com/xtimon/unified-sim
Project-URL: Documentation, https://github.com/xtimon/unified-sim#readme
Project-URL: Repository, https://github.com/xtimon/unified-sim.git
Project-URL: Issues, https://github.com/xtimon/unified-sim/issues
Project-URL: Changelog, https://github.com/xtimon/unified-sim/blob/main/CHANGELOG.md
Keywords: cosmology,simulation,quantum,n-body,physics,coherence,holographic,matter-genesis,universe
Classifier: Development Status :: 4 - Beta
Classifier: Intended Audience :: Science/Research
Classifier: License :: OSI Approved :: MIT License
Classifier: Programming Language :: Python :: 3
Classifier: Programming Language :: Python :: 3.9
Classifier: Programming Language :: Python :: 3.10
Classifier: Programming Language :: Python :: 3.11
Classifier: Programming Language :: Python :: 3.12
Classifier: Topic :: Scientific/Engineering :: Physics
Classifier: Topic :: Scientific/Engineering :: Astronomy
Requires-Python: >=3.9
License-File: LICENSE
Requires-Dist: numpy>=1.21.0
Requires-Dist: scipy>=1.7.0
Requires-Dist: matplotlib>=3.5.0
Requires-Dist: pandas>=1.3.0
Requires-Dist: tqdm>=4.64.0
Provides-Extra: gpu-cuda
Requires-Dist: cupy-cuda12x; extra == "gpu-cuda"
Provides-Extra: gpu-vulkan
Requires-Dist: vulkpy; extra == "gpu-vulkan"
Provides-Extra: gpu-opencl
Requires-Dist: pyopencl; extra == "gpu-opencl"
Provides-Extra: gpu-all
Requires-Dist: cupy-cuda12x; extra == "gpu-all"
Requires-Dist: vulkpy; extra == "gpu-all"
Requires-Dist: pyopencl; extra == "gpu-all"
Provides-Extra: dev
Requires-Dist: pytest>=7.0.0; extra == "dev"
Requires-Dist: pytest-cov>=4.0.0; extra == "dev"
Requires-Dist: black>=23.0.0; extra == "dev"
Requires-Dist: flake8>=6.0.0; extra == "dev"
Requires-Dist: mypy>=1.0.0; extra == "dev"
Requires-Dist: isort>=5.12.0; extra == "dev"
Requires-Dist: pre-commit>=3.0.0; extra == "dev"
Provides-Extra: docs
Requires-Dist: sphinx>=6.0.0; extra == "docs"
Requires-Dist: sphinx-rtd-theme>=1.2.0; extra == "docs"
Requires-Dist: sphinx-autobuild>=2021.3.14; extra == "docs"
Provides-Extra: jupyter
Requires-Dist: jupyter>=1.0.0; extra == "jupyter"
Requires-Dist: jupyterlab>=4.0.0; extra == "jupyter"
Requires-Dist: ipywidgets>=8.0.0; extra == "jupyter"
Provides-Extra: yaml
Requires-Dist: pyyaml>=6.0.0; extra == "yaml"
Provides-Extra: all
Requires-Dist: cosmic-unified-sim[dev,docs,gpu-cuda,jupyter,yaml]; extra == "all"
Dynamic: license-file
